ndx_ibl/__init__.py
ndx_ibl/spec/ndx-ibl.extensions.yaml
ndx_ibl/spec/ndx-ibl.namespace.yaml
tests/__init__.py
tests/test_ibl.py
ndx_ibl-0.1.0.dist-info/LICENSE.txt
ndx_ibl-0.1.0.dist-info/METADATA
ndx_ibl-0.1.0.dist-info/WHEEL
ndx_ibl-0.1.0.dist-info/top_level.txt
ndx_ibl-0.1.0.dist-info/RECORD
