Metadata-Version: 2.1
Name: ndx-ibl
Version: 0.1.0
Summary: IBL sessions specific metadata
Home-page: UNKNOWN
Author: Cody Baker
Author-email: cody.baker@catalystneuro.com
License: BSD 3-Clause
Platform: UNKNOWN
Classifier: Intended Audience :: Developers
Classifier: Intended Audience :: Science/Research
Requires-Dist: pynwb (>=1.3.0)
